{
  "main": {
    "id": "d2a65a9f0912ccd7",
    "type": "split",
    "children": [
      {
        "id": "e9c5571c71360414",
        "type": "tabs",
        "children": [
          {
            "id": "2a1b1325ec4d3ffb",
            "type": "leaf",
            "state": {
              "type": "markdown",
              "state": {
                "file": "Appunti unibo/Statistica/appunti/Statistica Inferenziale.md",
                "mode": "source",
                "source": false
              }
            }
          },
          {
            "id": "f49979258dba1449",
            "type": "leaf",
            "state": {
              "type": "markdown",
              "state": {
                "file": "Appunti unibo/Statistica/appunti/Indice.md",
                "mode": "source",
                "source": false
              }
            }
          }
        ]
      }
    ],
    "direction": "vertical"
  },
  "left": {
    "id": "a2c622ea08b5ecde",
    "type": "split",
    "children": [
      {
        "id": "19c32cee30ebbaf4",
        "type": "tabs",
        "children": [
          {
            "id": "c7691301ebb12b2c",
            "type": "leaf",
            "state": {
              "type": "file-explorer",
              "state": {
                "sortOrder": "alphabetical"
              }
            }
          },
          {
            "id": "3eed3da6a3ae0f05",
            "type": "leaf",
            "state": {
              "type": "search",
              "state": {
                "query": "",
                "matchingCase": false,
                "explainSearch": false,
                "collapseAll": false,
                "extraContext": false,
                "sortOrder": "alphabetical"
              }
            }
          },
          {
            "id": "cfc7e2185e373009",
            "type": "leaf",
            "state": {
              "type": "bookmarks",
              "state": {}
            }
          }
        ]
      }
    ],
    "direction": "horizontal",
    "width": 300
  },
  "right": {
    "id": "ce57f7da7695846d",
    "type": "split",
    "children": [
      {
        "id": "55e9165d300301a7",
        "type": "tabs",
        "children": [
          {
            "id": "7715255d42c93daf",
            "type": "leaf",
            "state": {
              "type": "backlink",
              "state": {
                "file": "Appunti unibo/Statistica/appunti/Statistica Inferenziale.md",
                "collapseAll": false,
                "extraContext": false,
                "sortOrder": "alphabetical",
                "showSearch": false,
                "searchQuery": "",
                "backlinkCollapsed": false,
                "unlinkedCollapsed": true
              }
            }
          },
          {
            "id": "de47d15c6e7334fc",
            "type": "leaf",
            "state": {
              "type": "outgoing-link",
              "state": {
                "file": "Appunti unibo/Statistica/appunti/Statistica Inferenziale.md",
                "linksCollapsed": false,
                "unlinkedCollapsed": true
              }
            }
          },
          {
            "id": "df969cf6e9d3f210",
            "type": "leaf",
            "state": {
              "type": "tag",
              "state": {
                "sortOrder": "frequency",
                "useHierarchy": true
              }
            }
          },
          {
            "id": "48ec05ecce9299c6",
            "type": "leaf",
            "state": {
              "type": "outline",
              "state": {
                "file": "Appunti unibo/Statistica/appunti/Statistica Inferenziale.md"
              }
            }
          }
        ],
        "currentTab": 3
      }
    ],
    "direction": "horizontal",
    "width": 200
  },
  "left-ribbon": {
    "hiddenItems": {
      "switcher:Apri selezione rapida": false,
      "graph:Apri vista grafo": false,
      "canvas:Crea nuova lavagna": false,
      "daily-notes:Apri nota del giorno": false,
      "templates:Inserisci modello": false,
      "command-palette:Apri riquadro comandi": false
    }
  },
  "active": "2a1b1325ec4d3ffb",
  "lastOpenFiles": [
    "Appunti unibo/Statistica/appunti/Indice.md",
    "Appunti unibo/Statistica/appunti/Statistica Inferenziale.md",
    "Appunti unibo/Statistica/appunti/Statistica Descrittiva.md",
    "Appunti unibo/Immagini/Pasted image 20240513155224.png",
    "Appunti unibo/Immagini/Pasted image 20240513154600.png",
    "Appunti unibo/Immagini/Pasted image 20240513154358.png",
    "Appunti unibo/Immagini/Pasted image 20240513153712.png",
    "Appunti unibo/Immagini/Pasted image 20240513153631.png",
    "Appunti unibo/Immagini/Pasted image 20240513153511.png",
    "Appunti unibo/Statistica/appunti/Terza Lezione.md",
    "Appunti unibo/Statistica/appunti/Seconda Lezione.md",
    "Appunti unibo/Statistica/appunti/Distribuzione normale.md",
    "Appunti unibo/Sistemi Operativi/Esercizi.md",
    "Appunti unibo/Sistemi Operativi/Nona Lezione.md",
    "Appunti unibo/Sistemi Operativi/Indice.md",
    "Appunti unibo/Sistemi Operativi/Sesta Lezione.md",
    "Appunti unibo/Immagini/Pasted image 20240507165804.png",
    "Appunti unibo/Statistica/appunti/Prima Lezione.md",
    "Appunti unibo/Sistemi Operativi/Dodicesima lezione.md",
    "Appunti unibo/Sistemi Operativi/Tredicesima Lezione.md",
    "Appunti unibo/Immagini/Pasted image 20240502120359.png",
    "Appunti unibo/Immagini/Pasted image 20240502120228.png",
    "Appunti unibo/Immagini/Pasted image 20240502120210.png",
    "Appunti unibo/Sistemi Operativi/Undicesima Lezione.md",
    "Appunti unibo/Statistica/appunti/Quarta lezione.md",
    "cacca",
    "SPERMA.md",
    "new yoo",
    "Appunti unibo/Senza nome.md",
    "rep",
    "new vault",
    "Nuova cartella",
    "Appunti unibo/Sistemi Operativi/Sistemi Operativi.iml",
    "Appunti unibo/Algoritmi/Files/Minimum spanning tree/Minimum spanning tree.iml",
    "Appunti unibo/Algoritmi/Files/Files.iml",
    "README.md",
    "Vault",
    "Appunti unibo",
    "Appunti unibo/Sistemi Operativi/Decima Lezione.md",
    "Appunti unibo/Strategia aziendale/Indice.md",
    "Appunti unibo/Strategia aziendale/Undicesima Lezione.md",
    "Appunti unibo/Strategia aziendale/Decima Lezione.md",
    "Appunti unibo/Strategia aziendale/Glossario.md",
    "N.B..md",
    "Appunti unibo/Sistemi Operativi/Progetto.md",
    "Appunti unibo/Sistemi Operativi/Tutor/Tutor 1.md",
    "Senza nome.canvas",
    "Sistemi Operativi/Senza nome.canvas"
  ]
}